astrobeckit/__init__.py
astrobeckit/automatic_resubmit.py
astrobeckit/papergirl.py
astrobeckit/synchronise_for_movie.py
astrobeckit-0.1.4.dist-info/licenses/LICENCE
astrobeckit-0.1.4.dist-info/METADATA
astrobeckit-0.1.4.dist-info/WHEEL
astrobeckit-0.1.4.dist-info/entry_points.txt
astrobeckit-0.1.4.dist-info/top_level.txt
astrobeckit-0.1.4.dist-info/RECORD
