Metadata-Version: 2.4
Name: astrobeckit
Version: 0.1.4
Summary: Useful quick scripts
Home-page: https://github.com/becnealon/becastro
Author: Rebecca Nealon
Author-email: Rebecca Nealon <rebecca.nealon.astro@gmail.com>
Project-URL: Source, https://github.com/becnealon/astrobeckit
Requires-Python: >=3.8
License-File: LICENCE
Requires-Dist: matplotlib>=3.6
Dynamic: author
Dynamic: home-page
Dynamic: license-file
Dynamic: requires-python
